pkgexampleconsole/__init__.py
pkgexampleconsole/helloworld.py
pkgexampleconsole/myscript.py
pkgexampleconsole-1.0.2.dist-info/LICENCE
pkgexampleconsole-1.0.2.dist-info/METADATA
pkgexampleconsole-1.0.2.dist-info/WHEEL
pkgexampleconsole-1.0.2.dist-info/entry_points.txt
pkgexampleconsole-1.0.2.dist-info/top_level.txt
pkgexampleconsole-1.0.2.dist-info/RECORD
