Metadata-Version: 2.1
Name: pkgexampleconsole
Version: 1.0.2
Summary: A console package example
Author-email: Good Boy <pythonic@rexbytes.com>
Project-URL: Homepage, https://github.com/RexBytes/pkgexampleconsole
Project-URL: Bug Tracker, https://github.com/RexBytes/pkgexampleconsole/issues
Project-URL: Download URL, https://github.com/RexBytes/pkgexampleconsole/archive/refs/tags/v1.0.2.tar.gz
Classifier: Programming Language :: Python :: 3
Classifier: License :: OSI Approved :: MIT License
Classifier: Operating System :: OS Independent
Requires-Python: >=3.7
License-File: LICENCE
